ncbuild/__init__.py
ncbuild/_attribute_values.py
ncbuild/_classes.py
ncbuild/_constants.py
ncbuild/_create_dataset.py
ncbuild/_create_nc.py
ncbuild/_create_ncml.py
ncbuild/_grid_mapping.py
ncbuild/_ncml_comments.py
ncbuild/_variable_identification.py
ncbuild/cf-area-type-table.xml
ncbuild/cf-standard-name-table.xml
ncbuild-0.0.3.dist-info/LICENSE
ncbuild-0.0.3.dist-info/METADATA
ncbuild-0.0.3.dist-info/WHEEL
ncbuild-0.0.3.dist-info/top_level.txt
ncbuild-0.0.3.dist-info/RECORD
