Metadata-Version: 2.1
Name: ncbuild
Version: 0.0.3
Summary: Used for generating netCDF files compliant with CF Conventions or ACDD
Home-page: https://github.com/jenochjones/ncbuild
Author: J Enoch Jones
Author-email: jonenochjones@gmail.com
Classifier: Programming Language :: Python :: 3
Classifier: License :: OSI Approved :: MIT License
Classifier: Operating System :: OS Independent
License-File: LICENSE
